open_atmos_jupyter_utils/__init__.py
open_atmos_jupyter_utils/notebook_vars.py
open_atmos_jupyter_utils/pip_install_on_colab.py
open_atmos_jupyter_utils/show_anim.py
open_atmos_jupyter_utils/show_plot.py
open_atmos_jupyter_utils/temporary_file.py
open_atmos_jupyter_utils-1.3.0.dist-info/LICENSE
open_atmos_jupyter_utils-1.3.0.dist-info/METADATA
open_atmos_jupyter_utils-1.3.0.dist-info/WHEEL
open_atmos_jupyter_utils-1.3.0.dist-info/top_level.txt
open_atmos_jupyter_utils-1.3.0.dist-info/RECORD
