Metadata-Version: 2.1
Name: open-atmos-jupyter-utils
Version: 1.3.0
Summary: utility routines used in PySDM, PyMPDATA and PyPartMC examples and tests
Home-page: https://github.com/open-atmos/jupyter-utils
License: GPL-3.0
Project-URL: Homepage, https://github.com/open-atmos/jupyter-utils
Project-URL: Source, https://github.com/open-atmos/jupyter-utils
Project-URL: Tracker, https://github.com/open-atmos/jupyter-utils/issues
Project-URL: Documentation, https://open-atmos.github.io/jupyter-utils
License-File: LICENSE
Requires-Dist: ipywidgets
Requires-Dist: IPython
Requires-Dist: matplotlib
Requires-Dist: imageio
Requires-Dist: nbformat
